LICENSE
MANIFEST.in
README.md
pyproject.toml
setup.py
src/wzero/__init__.py
src/wzero/binarization.py
src/wzero/experiments.py
src/wzero/mapping.py
src/wzero/metrics.py
src/wzero.egg-info/PKG-INFO
src/wzero.egg-info/SOURCES.txt
src/wzero.egg-info/dependency_links.txt
src/wzero.egg-info/not-zip-safe
src/wzero.egg-info/top_level.txt
src/wzero/datasets/__init__.py
src/wzero/datasets/dataset.py
src/wzero/datasets/image.py
src/wzero/datasets/image_rgb.py
src/wzero/datasets/utils.py
src/wzero/datasets/datasets/__init__.py
src/wzero/datasets/datasets/cifar10.py
src/wzero/datasets/datasets/ecoli.py
src/wzero/datasets/datasets/eeg_eye_state.py
src/wzero/datasets/datasets/fashion_mnist.py
src/wzero/datasets/datasets/glass.py
src/wzero/datasets/datasets/landsat.py
src/wzero/datasets/datasets/magic_gamma_telescope.py
src/wzero/datasets/datasets/mnist.py
src/wzero/datasets/datasets/segment.py
src/wzero/datasets/datasets/shuttle.py
src/wzero/datasets/datasets/vehicle.py
src/wzero/models/__init__.py
src/wzero/models/bleaching_bloom_wisard.py
src/wzero/models/bleaching_wisard.py
src/wzero/models/bloom_wisard.py
src/wzero/models/regression_wisard.py
src/wzero/models/wisard.py
src/wzero/models/cc/base_classes.h
src/wzero/models/cc/bleaching_bloom_wisard.cc
src/wzero/models/cc/bleaching_wisard.cc
src/wzero/models/cc/bloom_wisard.cc
src/wzero/models/cc/regression_wisard.cc
src/wzero/models/cc/wisard.cc
src/wzero/models/cc/include/thread_pool.hpp
src/wzero/models/cc/utils/array.h
src/wzero/models/cc/utils/atomic_operators.h
src/wzero/models/cc/utils/mapping.cc
src/wzero/models/cc/utils/mapping.h
src/wzero/models/cc/utils/utils.cc
src/wzero/models/cc/utils/utils.h
src/wzero/models/wrappers/CMakeLists.txt
src/wzero/models/wrappers/__init__.py
src/wzero/models/wrappers/base_bind.h
src/wzero/models/wrappers/bleaching_bloom_wisard_bind.cc
src/wzero/models/wrappers/bleaching_wisard_bind.cc
src/wzero/models/wrappers/bloom_wisard_bind.cc
src/wzero/models/wrappers/regression_wisard_bind.cc
src/wzero/models/wrappers/wisard_bind.cc
src/wzero/models/wrappers/wnnc.cc
src/wzero/models/wrappers/utils/array_conversion.h
src/wzero/utils/__init__.py
