Metadata-Version: 2.1
Name: wzero
Version: 0.0.1
Summary: Weightless Neural Network Library
Author: Alan Bacellar
Author-email: alanbacellar@gmail.com
License: UNKNOWN
Platform: UNKNOWN
Requires-Python: >=3.6
License-File: LICENSE
